setup.py
unittest_onerror.py
unittest_onerror.egg-info/PKG-INFO
unittest_onerror.egg-info/SOURCES.txt
unittest_onerror.egg-info/dependency_links.txt
unittest_onerror.egg-info/requires.txt
unittest_onerror.egg-info/top_level.txt