Metadata-Version: 1.1
Name: unittest-onerror
Version: 0.1
Summary: Declarative error and failure catching for Python unittest module
Home-page: https://github.com/absent1706/unittest_onerror
Author: Alexander Litvinenko
Author-email: litvinenko1706@gmail.com
License: MIT
Keywords: unittest
Platform: any
Classifier: Development Status :: 4 - Beta
Classifier: Environment :: Web Environment
Classifier: Intended Audience :: Developers
Classifier: License :: OSI Approved :: MIT License
Classifier: Programming Language :: Python :: 2
Classifier: Programming Language :: Python :: 2.7
Classifier: Programming Language :: Python :: Implementation :: CPython
Classifier: Topic :: Database
